{"data":{"allMarkdownRemark":{"edges":[{"node":{"excerpt":"Hire Me need a graphics guy? Looking for hand-crafted, high-end, interactive 3D experiences for your website or product? I’m available for…","fields":{"slug":"/hire/"},"frontmatter":{"date":"August 04, 2018","title":"Hire"}}},{"node":{"excerpt":"Far far away, behind the word mountains, far from the countries Vokalia and\nConsonantia, there live the blind texts. Separated they live in…","fields":{"slug":"/posts/hi-folks/"},"frontmatter":{"date":"May 28, 2015","title":"New Beginnings"}}}]}},"pageContext":{}}